stepfunction/constants/__init__.py
stepfunction/constants/enums.py
stepfunction/constants/visualizer.py
stepfunction/core/step_function/__init__.py
stepfunction/core/step_function/step_function.py
stepfunction/core/visualizer/__init__.py
stepfunction/core/visualizer/visualizer.py
stepfunction/exceptions/__init__.py
stepfunction/exceptions/step_errors.py
stepfunction/types/__init__.py
stepfunction/types/step_types.py
stepfunction/types/visualizer_types.py
stepfunction/utils/__init__.py
stepfunction/utils/constants.py
stepfunction/utils/logger.py
stepfunction/utils/utils.py
stepfunction-0.0.1.dist-info/LICENSE
stepfunction-0.0.1.dist-info/METADATA
stepfunction-0.0.1.dist-info/WHEEL
stepfunction-0.0.1.dist-info/top_level.txt
stepfunction-0.0.1.dist-info/RECORD
