Metadata-Version: 2.1
Name: stepfunction
Version: 0.0.1
Summary: Step Function Workflow Orchestration Library
Author: Vineeth Penugonda
Project-URL: Homepage, https://github.com/vinecodes/stepfunction
Project-URL: Issues, https://github.com/vinecodes/stepfunction/issues
Project-URL: Blog_Post, https://blog.vineethp.com/posts/introducingstepfunction/
Keywords: StepFunction,Workflow,Orchestration,Library
Classifier: Programming Language :: Python :: 3
Classifier: Programming Language :: Python :: 3.12
Classifier: Operating System :: OS Independent
Classifier: Development Status :: 3 - Alpha
Classifier: License :: OSI Approved :: MIT License
Classifier: Topic :: Software Development :: Libraries
Requires-Python: >=3.12
License-File: LICENSE
Requires-Dist: graphviz ===0.20.3
